bend/__init__.py
bend-0.0.1.dist-info/METADATA
bend-0.0.1.dist-info/WHEEL
bend-0.0.1.dist-info/entry_points.txt
bend-0.0.1.dist-info/top_level.txt
bend-0.0.1.dist-info/RECORD
